Workbook

Sheet Config
A1: CONFIGURATION PARAMETERS
A3: Parameter | B3: Value | C3: Description
A4: Target_ROI | B4: 200 | C4: Minimum acceptable ROI
A5: Target_CPL | B5: 40 | C5: Target Cost per Lead (₹)
A6: Target_NCA_pct | B6: 22 | C6: Target New Customer Acquisition %
A7: Target_L_to_AS_pct | B7: 65 | C7: Target Lead to Appointment Schedule %
A8: Target_AS_to_WI_pct | B8: 75 | C8: Target Appointment to Walk-in %
A9: M3_Retention_Rate | B9: 0.45 | C9: Expected M3 retention rate
A10: M6_Retention_Rate | B10: 0.3 | C10: Expected M6 retention rate
A11: M9_Retention_Rate | B11: 0.2 | C11: Expected M9 retention rate
A12: Paid_Budget_Split_Google_pct | B12: 70 | C12: Google share of paid budget
A13: Paid_Budget_Split_Meta_pct | B13: 30 | C13: Meta share of paid budget
A14: GMB_Growth_Rate_pct | B14: 5 | C14: Monthly GMB channel growth
A15: Website_Organic_Growth_pct | B15: 3 | C15: Monthly website organic growth
A16: App_Organic_Growth_pct | B16: 8 | C16: Monthly app organic growth

Sheet Core_Digital
A1: Year | B1: Month | C1: Month_Num | D1: Perf_Spends | E1: Impressions | F1: Clicks | G1: CPM | H1: CPC | I1: CTR_pct | J1: Panel_Leads | K1: Panel_CPL | L1: Leads | M1: AS | N1: Walkin | O1: Total_Rev | P1: Exist_Rev | Q1: Diag_Rev | R1: CPL | S1: L_to_AS_pct | T1: AS_to_WI_pct | U1: ROI | V1: AOV | W1: NCA | X1: New_Rev | Y1: Cost_per_NCA | Z1: New_ROI | AA1: New_AOV | AB1: NCA_pct | AC1: New_Rev_pct | AD1: Transactions | AE1: New_Trans
A2: 2024 | B2: November | C2: 1 | D2: 4998502 | E2: 28430647 | F2: 1471323 | G2: 176 | H2: 3 | I2: 5.18 | J2: 69135 | K2: 72 | L2: 116750 | M2: 45437 | N2: 37999 | O2: 578766770 | P2: 479551016 | Q2: 99215754 | R2: 43 | S2: 39 | T2: 84 | U2: 115.79 | V2: 15231 | W2: 7685 | X2: 236753680 | Y2: 650 | Z2: 47.36 | AA2: 30807 | AB2: 20 | AC2: 40.91 | AD2: 69064 | AE2: 17478
A3: 2024 | B3: December | C3: 2 | D3: 4478891 | E3: 21574013 | F3: 1283641 | G3: 208 | H3: 3 | I3: 5.95 | J3: 50205 | K3: 89 | L3: 103248 | M3: 46208 | N3: 38752 | O3: 621001341 | P3: 483129551 | Q3: 137871789 | R3: 43 | S3: 45 | T3: 84 | U3: 138.65 | V3: 16025 | W3: 7730 | X3: 239247158 | Y3: 579 | Z3: 53.42 | AA3: 30950 | AB3: 20 | AC3: 38.53 | AD3: 70584 | AE3: 17638
A4: 2025 | B4: January | C4: 3 | D4: 2111505 | E4: 8390150 | F4: 504968 | G4: 252 | H4: 4 | I4: 6.02 | J4: 21060 | K4: 100 | L4: 76814 | M4: 45072 | N4: 38604 | O4: 655731988 | P4: 481653777 | Q4: 174078211 | R4: 27 | S4: 59 | T4: 86 | U4: 310.55 | V4: 16986 | W4: 7068 | X4: 245782313 | Y4: 299 | Z4: 116.4 | AA4: 34774 | AB4: 18 | AC4: 37.48 | AD4: 69883 | AE4: 16718
A5: 2025 | B5: February | C5: 4 | D5: 2098582 | E5: 9559845 | F5: 522229 | G5: 220 | H5: 4 | I5: 5.46 | J5: 21528 | K5: 97 | L5: 78633 | M5: 44634 | N5: 37220 | O5: 559328253 | P5: 403725554 | Q5: 155602699 | R5: 27 | S5: 57 | T5: 83 | U5: 266.53 | V5: 15028 | W5: 6738 | X5: 188151945 | Y5: 311 | Z5: 89.66 | AA5: 27924 | AB5: 18 | AC5: 33.64 | AD5: 65805 | AE5: 14756
A6: 2025 | B6: March | C6: 5 | D6: 2663639 | E6: 9584065 | F6: 192308 | G6: 278 | H6: 14 | I6: 2.01 | J6: 9055 | K6: 294 | L6: 69834 | M6: 46065 | N6: 38923 | O6: 619373502 | P6: 434521474 | Q6: 184852027 | R6: 38 | S6: 66 | T6: 84 | U6: 232.53 | V6: 15913 | W6: 7611 | X6: 215386981 | Y6: 350 | Z6: 80.86 | AA6: 28299 | AB6: 20 | AC6: 34.77 | AD6: 70247 | AE6: 17189
A7: 2025 | B7: April | C7: 6 | D7: 2268827 | E7: 8343778 | F7: 49733 | G7: 272 | H7: 46 | I7: 0.6 | J7: 3238 | K7: 701 | L7: 56804 | M7: 40213 | N7: 36910 | O7: 621074885 | P7: 453223806 | Q7: 167851079 | R7: 40 | S7: 71 | T7: 92 | U7: 273.74 | V7: 16827 | W7: 7080 | X7: 219206427 | Y7: 320 | Z7: 96.62 | AA7: 30961 | AB7: 19 | AC7: 35.29 | AD7: 65379 | AE7: 15918
A8: 2025 | B8: May | C8: 7 | D8: 2645859 | E8: 24977267 | F8: 125280 | G8: 106 | H8: 21 | I8: 0.5 | J8: 4541 | K8: 583 | L8: 57682 | M8: 39501 | N8: 29507 | O8: 508913754 | P8: 332306503 | Q8: 176607250 | R8: 46 | S8: 68 | T8: 75 | U8: 192.34 | V8: 17247 | W8: 6417 | X8: 160878395 | Y8: 412 | Z8: 60.8 | AA8: 25071 | AB8: 22 | AC8: 31.61 | AD8: 51682 | AE8: 13763
A9: 2025 | B9: June | C9: 8 | D9: 2466356 | E9: 20012031 | F9: 133182 | G9: 123 | H9: 19 | I9: 0.67 | J9: 3760 | K9: 656 | L9: 56591 | M9: 41412 | N9: 36114 | O9: 667163529 | P9: 405475155 | Q9: 261688374 | R9: 44 | S9: 73 | T9: 87 | U9: 270.51 | V9: 18474 | W9: 7310 | X9: 196390716 | Y9: 337 | Z9: 79.63 | AA9: 26866 | AB9: 20 | AC9: 29.44 | AD9: 64161 | AE9: 16137
A10: 2025 | B10: July | C10: 9 | D10: 3742107 | E10: 49669038 | F10: 327261 | G10: 75 | H10: 11 | I10: 0.66 | J10: 6134 | K10: 610 | L10: 70086 | M10: 48622 | N10: 36281 | O10: 680785043 | P10: 394882706 | Q10: 285902337 | R10: 53 | S10: 69 | T10: 75 | U10: 181.93 | V10: 18764 | W10: 7788 | X10: 197932414 | Y10: 480 | Z10: 52.89 | AA10: 25415 | AB10: 21 | AC10: 29.07 | AD10: 65791 | AE10: 16813
A11: 2025 | B11: August | C11: 10 | D11: 2615129 | E11: 21222673 | F11: 181208 | G11: 123 | H11: 14 | I11: 0.85 | J11: 3567 | K11: 733 | L11: 74270 | M11: 51720 | N11: 38905 | O11: 594092535 | P11: 381592054 | Q11: 212500481 | R11: 35 | S11: 70 | T11: 75 | U11: 227.18 | V11: 15270 | W11: 8049 | X11: 176317559 | Y11: 325 | Z11: 67.42 | AA11: 21906 | AB11: 21 | AC11: 29.68 | AD11: 71195 | AE11: 17137
A12: 2025 | B12: September | C12: 11 | D12: 1781732 | E12: 14720543 | F12: 173614 | G12: 121 | H12: 10 | I12: 1.18 | J12: 8369 | K12: 213 | L12: 78393 | M12: 52816 | N12: 34196 | O12: 745082575 | P12: 417186283 | Q12: 327896293 | R12: 23 | S12: 67 | T12: 65 | U12: 418.18 | V12: 21789 | W12: 7877 | X12: 207383745 | Y12: 226 | Z12: 116.39 | AA12: 26328 | AB12: 23 | AC12: 27.83 | AD12: 66492 | AE12: 17509
A13: 2025 | B13: October | C13: 12 | D13: 2056651 | E13: 9324238 | F13: 413476 | G13: 221 | H13: 5 | I13: 4.43 | J13: 3512 | K13: 586 | L13: 71260 | M13: 50672 | N13: 30735 | O13: 662424512 | P13: 385070189 | Q13: 277354323 | R13: 29 | S13: 71 | T13: 61 | U13: 322.09 | V13: 21553 | W13: 7350 | X13: 216933118 | Y13: 280 | Z13: 105.48 | AA13: 29515 | AB13: 24 | AC13: 32.75 | AD13: 58042 | AE13: 16564
A14: TTM | B14: Nov24-Oct25 | C14: 12 | D14: =SUM(D2:D13) | E14: =SUM(E2:E13) | F14: =SUM(F2:F13) | G14: =AVERAGE(G2:G13) | H14: =AVERAGE(H2:H13) | I14: =AVERAGE(I2:I13) | J14: =AVERAGE(J2:J13) | K14: =AVERAGE(K2:K13) | L14: =SUM(L2:L13) | M14: =SUM(M2:M13) | N14: =SUM(N2:N13) | O14: =SUM(O2:O13) | P14: =SUM(P2:P13) | Q14: =SUM(Q2:Q13) | R14: =AVERAGE(R2:R13) | S14: =AVERAGE(S2:S13) | T14: =AVERAGE(T2:T13) | U14: =AVERAGE(U2:U13) | V14: =SUM(V2:V13) | W14: =SUM(W2:W13) | X14: =AVERAGE(X2:X13) | Y14: =AVERAGE(Y2:Y13) | Z14: =AVERAGE(Z2:Z13) | AA14: =SUM(AA2:AA13) | AB14: =SUM(AB2:AB13) | AC14: =AVERAGE(AC2:AC13) | AD14: =AVERAGE(AD2:AD13) | AE14: =AVERAGE(AE2:AE13)
A15: 3M_Avg | B15: Aug-Oct | C15: 3 | D15: =AVERAGE(D11:D13) | E15: =AVERAGE(E11:E13) | F15: =AVERAGE(F11:F13) | G15: =AVERAGE(G11:G13) | H15: =AVERAGE(H11:H13) | I15: =AVERAGE(I11:I13) | J15: =AVERAGE(J11:J13) | K15: =AVERAGE(K11:K13) | ... AE15: =AVERAGE(AE11:AE13)

Sheet Google_Web
A1: Year | B1: Month | C1: Perf_Spends | D1: Impressions | E1: Clicks | F1: Leads | G1: AS | H1: Walkin | I1: Total_Rev | J1: Exist_Rev | K1: NCA | L1: New_Rev
A2: 2024 | B2: November | C2: 4149705 | D2: 18574646 | E2: 1446494 | F2: 54944 | G2: 1625 | H2: 1352 | I2: 21735754 | J2: 16719811 | K2: 237 | L2: 9768803
A3: 2024 | B3: December | C3: 3640526 | D3: 14958714 | E3: 1267608 | F3: 40642 | G3: 1033 | H3: 846 | I3: 18444130 | J3: 12003021 | K3: 148 | L3: 4652470
A4: 2025 | B4: January | C4: 1835813 | D4: 5540980 | E4: 495565 | F4: 20191 | G4: 3503 | H4: 2649 | I4: 47064190 | J4: 35810455 | K4: 468 | L4: 14360537
A5: 2025 | B5: February | C5: 1798760 | D5: 5715661 | E5: 507035 | F5: 24486 | G5: 5533 | H5: 4292 | I5: 63657904 | J5: 53396504 | K5: 790 | L5: 19331196
A6: 2025 | B6: March | C6: 1772998 | D6: 2086448 | E6: 162795 | F6: 10185 | G6: 3947 | H6: 3308 | I6: 48125140 | J6: 35167233 | K6: 622 | L6: 15152545
A7: 2025 | B7: April | C7: 1454026 | D7: 350527 | E7: 17193 | F7: 4421 | G7: 2841 | H7: 2434 | I7: 44478156 | J7: 32982040 | K7: 510 | L7: 15810449
A8: 2025 | B8: May | C8: 1353780 | D8: 391216 | E8: 16134 | F8: 4211 | G8: 2703 | H8: 1750 | I8: 36161226 | J8: 23498499 | K8: 530 | L8: 8924367
A9: 2025 | B9: June | C9: 1261033 | D9: 812196 | E9: 44959 | F9: 5247 | G9: 3459 | H9: 2031 | I9: 46070314 | J9: 27773082 | K9: 580 | L9: 12220722
A10: 2025 | B10: July | C10: 1575980 | D10: 1347480 | E10: 104109 | F10: 9424 | G10: 5650 | H10: 3642 | I10: 72573645 | J10: 49878136 | K10: 1079 | L10: 23147943
A11: 2025 | B11: August | C11: 1362648 | D11: 1143884 | E11: 91284 | F11: 10194 | G11: 6257 | H11: 3709 | I11: 68719694 | J11: 53395403 | K11: 997 | L11: 26068864
A12: 2025 | B12: September | C12: 1452432 | D12: 1793153 | E12: 91035 | F12: 3595 | G12: 2229 | H12: 1432 | I12: 38023638 | J12: 18559696 | K12: 320 | L12: 10205045
A13: 2025 | B13: October | C13: 1938412 | D13: 5113281 | E13: 376933 | F13: 4038 | G13: 2227 | H13: 1471 | I13: 34727877 | J13: 17648919 | K13: 298 | L13: 10225071
A14: TTM | C14: =SUM(C2:C13) | D14: =SUM(D2:D13) | E14: =SUM(E2:E13) | F14: =SUM(F2:F13) | G14: =SUM(G2:G13) | H14: =SUM(H2:H13) | I14: =SUM(I2:I13) | J14: =SUM(J2:J13) | ... L14: =SUM(L2:L13)

Sheet Meta_Web
A1: Year | B1: Month | C1: Perf_Spends | D1: Impressions | E1: Clicks | F1: Leads | G1: AS | H1: Walkin | I1: Total_Rev | J1: Exist_Rev | K1: NCA | L1: New_Rev
A2: 2024 | B2: November | C2: 848797 | D2: 9856001 | E2: 24829 | F2: 436 | G2: 15 | H2: 59 | I2: 2865972 | J2: 2809776 | K2: 0 | L2: 0
A3: 2024 | B3: December | C3: 838365 | D3: 6615299 | E3: 16033 | F3: 583 | G3: 62 | H3: 123 | I3: 3921010 | J3: 3849220 | K3: 0 | L3: 0
A4: 2025 | B4: January | C4: 275692 | D4: 2849170 | E4: 9403 | F4: 68 | G4: 1 | H4: 4 | I4: 78798 | J4: 4650 | K4: 0 | L4: 0
A5: 2025 | B5: February | C5: 299822 | D5: 3844184 | E5: 15194 | F5: 4 | G5: 1 | H5: 3 | I5: 101857 | J5: 3000 | K5: 0 | L5: 0
A6: 2025 | B6: March | C6: 890641 | D6: 7497617 | E6: 29513 | F6: 1570 | G6: 476 | H6: 147 | I6: 934876 | J6: 840163 | K6: 0 | L6: 0
A7: 2025 | B7: April | C7: 814801 | D7: 7993251 | E7: 32540 | F7: 1188 | G7: 319 | H7: 102 | I7: 836984 | J7: 766387 | K7: 0 | L7: 0
A8: 2025 | B8: May | C8: 1292079 | D8: 24586051 | E8: 109146 | F8: 2057 | G8: 89 | H8: 30 | I8: 424920 | J8: 330373 | K8: 15 | L8: 85899
A9: 2025 | B9: June | C9: 1205323 | D9: 19199835 | E9: 88223 | F9: 178 | G9: 44 | H9: 60 | I9: 886490 | J9: 635644 | K9: 25 | L9: 356267
A10: 2025 | B10: July | C10: 2166127 | D10: 48321558 | E10: 223152 | F10: 2976 | G10: 93 | H10: 126 | I10: 3146439 | J10: 2786644 | K10: 52 | L10: 2115176
A11: 2025 | B11: August | C11: 1252481 | D11: 20078789 | E11: 89924 | F11: 1666 | G11: 51 | H11: 234 | I11: 2205523 | J11: 2093234 | K11: 79 | L11: 1678889
A12: 2025 | B12: September | C12: 329300 | D12: 12927390 | E12: 82579 | F12: 404 | G12: 5 | H12: 8 | I12: 157505 | J12: 11650 | K12: 0 | L12: 0
A13: 2025 | B13: October | C13: 118239 | D13: 4210957 | E13: 36543 | F13: 17 | G13: 0 | H13: 3 | I13: 140264 | J13: 5450 | K13: 0 | L13: 0
A14: TTM | C14: =SUM(C2:C13) | D14: =SUM(D2:D13) | E14: =SUM(E2:E13) | F14: =SUM(F2:F13) | G14: =SUM(G2:G13) | H14: =SUM(H2:H13) | I14: =SUM(I2:I13) | J14: =SUM(J2:J13) | ... L14: =SUM(L2:L13)

Sheet GMB
A1: Year | B1: Month | C1: Views | D1: Clicks | E1: Leads | F1: AS | G1: Walkin | H1: Total_Rev | I1: Exist_Rev | J1: NCA | K1: New_Rev
A2: 2024 | B2: November | C2: 490368 | D2: 73054 | E2: 42267 | F2: 28540 | G2: 20785 | H2: 335197985 | I2: 279331654 | J2: 5155 | K2: 149388768
A3: 2024 | B3: December | C3: 492030 | D3: 78333 | E3: 41355 | F3: 28312 | G3: 21243 | H3: 376277984 | I3: 286797434 | J3: 5256 | K3: 146973251
A4: 2025 | B4: January | C4: 510419 | D4: 84776 | E4: 34910 | F4: 24150 | G4: 18475 | H4: 334341446 | I4: 231601809 | J4: 4167 | K4: 124829548
A5: 2025 | B5: February | C5: 450355 | D5: 79064 | E5: 34464 | F5: 23155 | G5: 18602 | H5: 293417450 | I5: 205951481 | J5: 4050 | K5: 97635479
A6: 2025 | B6: March | C6: 490769 | D6: 85418 | E6: 36287 | F6: 24242 | G6: 18798 | H6: 314741828 | I6: 215854176 | J6: 4288 | K6: 114545950
A7: 2025 | B7: April | C7: 497271 | D7: 79024 | E7: 32904 | F7: 21130 | G7: 17136 | H7: 310637262 | I7: 224111115 | J7: 3910 | K7: 112680027
A8: 2025 | B8: May | C8: 533541 | D8: 80877 | E8: 33304 | F8: 21016 | G8: 14335 | H8: 263201202 | I8: 174597259 | J8: 3730 | K8: 90446849
A9: 2025 | B9: June | C9: 468916 | D9: 134574 | E9: 35319 | F9: 22699 | G9: 15506 | H9: 299202837 | I9: 176406020 | J9: 4080 | K9: 94789840
A10: 2025 | B10: July | C10: 426194 | D10: 174201 | E10: 37949 | F10: 24829 | G10: 20226 | H10: 393636770 | I10: 223608434 | J10: 4927 | K10: 119212056
A11: 2025 | B11: August | C11: 603587 | D11: 195595 | E11: 41744 | F11: 27048 | G11: 19656 | H11: 317692095 | I11: 194903662 | J11: 4749 | K11: 94596958
A12: 2025 | B12: September | C12: 611511 | D12: 192880 | E12: 49682 | F12: 33077 | G12: 20327 | H12: 450625285 | I12: 255877696 | J12: 5533 | K12: 129252954
A13: 2025 | B13: October | C13: 570044 | D13: 175850 | E13: 44649 | F13: 31703 | G13: 17419 | H13: 406659956 | I13: 245508895 | J13: 4923 | K13: 137773625
A14: TTM | C14: =SUM(C2:C13) | D14: =SUM(D2:D13) | E14: =SUM(E2:E13) | F14: =SUM(F2:F13) | G14: =SUM(G2:G13) | H14: =SUM(H2:H13) | I14: =SUM(I2:I13) | J14: =SUM(J2:J13) | K14: =SUM(K2:K13)

Sheet Website_Organic
A1: Year | B1: Month | C1: Leads | D1: AS | E1: Walkin | F1: Total_Rev | G1: Exist_Rev | H1: NCA | I1: New_Rev
A2: 2024 | B2: November | C2: 11407 | D2: 10626 | E2: 11890 | F2: 170025728 | G2: 136020582 | H2: 1647 | I2: 62253112
A3: 2024 | B3: December | C3: 11955 | D3: 11153 | E3: 11365 | F3: 168268127 | G3: 136446921 | H3: 1572 | I3: 65041329
A4: 2025 | B4: January | C4: 12839 | D4: 11974 | E4: 11853 | F4: 204916448 | G4: 158540467 | H4: 1727 | I4: 76062444
A5: 2025 | B5: February | C5: 12046 | D5: 11309 | E5: 10663 | F5: 153081359 | G5: 107187548 | H5: 1403 | I5: 53741509
A6: 2025 | B6: March | C6: 13715 | D6: 12756 | E6: 12312 | F6: 193735264 | G6: 136957730 | H6: 2047 | I6: 67266815
A7: 2025 | B7: April | C7: 12555 | D7: 11549 | E7: 12320 | F7: 203211919 | G7: 147252317 | H7: 2058 | I7: 65222876
A8: 2025 | B8: May | C8: 12631 | D8: 11498 | E8: 9231 | F8: 158287830 | G8: 96794255 | H8: 1452 | I8: 41950381
A9: 2025 | B9: June | C9: 12009 | D9: 11617 | E9: 13270 | F9: 246584843 | G9: 147268482 | H9: 2105 | I9: 63918850
A10: 2025 | B10: July | C10: 14753 | D10: 13725 | E10: 7808 | F10: 148279707 | G10: 76096196 | H10: 1360 | I10: 31690513
A11: 2025 | B11: August | C11: 15450 | D11: 14122 | E11: 11178 | F11: 161626501 | G11: 102987227 | H11: 1948 | I11: 41249686
A12: 2025 | B12: September | C12: 15072 | D12: 13530 | E12: 9538 | F12: 192920100 | G12: 103364336 | H12: 1809 | I12: 47715669
A13: 2025 | B13: October | C13: 14106 | D13: 13234 | E13: 9567 | F13: 182233659 | G13: 103277837 | H13: 1930 | I13: 55795884
A14: TTM | C14: =SUM(C2:C13) | D14: =SUM(D2:D13) | E14: =SUM(E2:E13) | F14: =SUM(F2:F13) | G14: =SUM(G2:G13) | H14: =SUM(H2:H13) | I14: =SUM(I2:I13)

Sheet Aggregator
A1: Year | B1: Month | C1: Leads | D1: AS | E1: Walkin | F1: Total_Rev | G1: Exist_Rev | H1: NCA | I1: New_Rev
A2: 2024 | B2: November | C2: 4972 | D2: 1999 | E2: 1182 | F2: 10088397 | G2: 8406998 | H2: 458 | I2: 4221954
A3: 2024 | B3: December | C3: 5160 | D3: 2182 | E3: 1199 | F3: 15076399 | G3: 12222331 | H3: 460 | I3: 4883686
A4: 2025 | B4: January | C4: 5670 | D4: 2427 | E4: 1241 | F4: 14316462 | G4: 10925699 | H4: 436 | I4: 7312986
A5: 2025 | B5: February | C5: 4695 | D5: 1776 | E5: 1012 | F5: 17235174 | G5: 14921910 | H5: 334 | I5: 4707951
A6: 2025 | B6: March | C6: 5112 | D6: 1779 | E6: 1425 | F6: 21550876 | G6: 17608907 | H6: 488 | I6: 7308102
A7: 2025 | B7: April | C7: 2332 | D7: 1130 | E7: 1000 | F7: 11945724 | G7: 9289406 | H7: 322 | I7: 4389422
A8: 2025 | B8: May | C8: 2040 | D8: 923 | E8: 1048 | F8: 13517500 | G8: 10291011 | H8: 412 | I8: 4333730
A9: 2025 | B9: June | C9: 448 | D9: 206 | E9: 621 | F9: 7781979 | G9: 4124840 | H9: 200 | I9: 2076968
A10: 2025 | B10: July | C10: 870 | D10: 315 | E10: 301 | F10: 4755741 | G10: 1568893 | H10: 70 | I10: 746720
A11: 2025 | B11: August | C11: 1171 | D11: 402 | E11: 383 | F11: 3401472 | G11: 1026385 | H11: 93 | I11: 291953
A12: 2025 | B12: September | C12: 5831 | D12: 354 | E12: 341 | F12: 8639790 | G12: 4616679 | H12: 121 | I12: 2000535
A13: 2025 | B13: October | C13: 5692 | D13: 814 | E13: 361 | F13: 6558889 | G13: 2889041 | H13: 134 | I13: 2031835
A14: TTM | C14: =SUM(C2:C13) | D14: =SUM(D2:D13) | E14: =SUM(E2:E13) | F14: =SUM(F2:F13) | G14: =SUM(G2:G13) | H14: =SUM(H2:H13) | I14: =SUM(I2:I13)

Sheet App_Organic
A1: Year | B1: Month | C1: Leads | D1: AS | E1: Walkin | F1: Total_Rev | G1: Exist_Rev | H1: NCA | I1: New_Rev
A2: 2024 | B2: November | C2: 2724 | D2: 2632 | E2: 2149 | F2: 28498132 | G2: 25907393 | H2: 229 | I2: 11173374
A3: 2024 | B3: December | C3: 3553 | D3: 3466 | E3: 2689 | F3: 37379476 | G3: 30176409 | H3: 230 | I3: 14255906
A4: 2025 | B4: January | C4: 3136 | D4: 3017 | E4: 2793 | F4: 45410052 | G4: 35166104 | H4: 247 | I4: 19107655
A5: 2025 | B5: February | C5: 2938 | D5: 2860 | E5: 2696 | F5: 35380177 | G5: 25810779 | H5: 212 | I5: 11676686
A6: 2025 | B6: March | C6: 2965 | D6: 2865 | E6: 2870 | F6: 43736438 | G6: 31544186 | H6: 217 | I6: 13306763
A7: 2025 | B7: April | C7: 3404 | D7: 3244 | E7: 3483 | F7: 56748667 | G7: 45606368 | H7: 292 | I7: 23013353
A8: 2025 | B8: May | C8: 3439 | D8: 3272 | E8: 2168 | F8: 35502719 | G8: 24976750 | H8: 222 | I8: 14571544
A9: 2025 | B9: June | C9: 3390 | D9: 3387 | E9: 3561 | F9: 61257382 | G9: 43887402 | H9: 276 | I9: 21367115
A10: 2025 | B10: July | C10: 4114 | D10: 4010 | E10: 3070 | F10: 51222445 | G10: 33774106 | H10: 262 | I10: 18962208
A11: 2025 | B11: August | C11: 4045 | D11: 3840 | E11: 3323 | F11: 42916766 | G11: 29655658 | H11: 215 | I11: 13658128
A12: 2025 | B12: September | C12: 3809 | D12: 3621 | E12: 2743 | F12: 64569109 | G12: 44609078 | H12: 210 | I12: 21965227
A13: 2025 | B13: October | C13: 2758 | D13: 2694 | E13: 2044 | F13: 41963031 | G13: 25599212 | H13: 150 | I13: 14862038
A14: TTM | C14: =SUM(C2:C13) | D14: =SUM(D2:D13) | E14: =SUM(E2:E13) | F14: =SUM(F2:F13) | G14: =SUM(G2:G13) | H14: =SUM(H2:H13) | I14: =SUM(I2:I13)

Sheet LTV_Cohorts
A1: Cohort | B1: Segment | C1: M0_Acquisitions | D1: M0_Revenue | E1: M3_Revenue | F1: M6_Revenue | G1: M9_Revenue | H1: LTV_Current | I1: M3_Retention% | J1: M6_Retention% | K1: M9_Retention%
A2: Dec-24 | B2: Overall | C2: 7730 | D2: 239247158 | E2: 180000000 | F2: 120000000 | G2: 80000000 | H2: 45592 | I2: =IF(E2>0,E2/D2,0) | J2: =IF(F2>0,F2/D2,0) | K2: =IF(G2>0,G2/D2,0)
A3: Jan-25 | B3: Overall | C3: 7068 | D3: 245782313 | E3: 170000000 | F3: 110000000 | G3: 65000000 | H3: 43178 | I3: =IF(E3>0,E3/D3,0) | J3: =IF(F3>0,F3/D3,0) | K3: =IF(G3>0,G3/D3,0)
A4: Feb-25 | B4: Overall | C4: 6738 | D4: 188151945 | E4: 140000000 | F4: 90000000 | G4: 50000000 | H4: 37482 | I4: =IF(E4>0,E4/D4,0) | J4: =IF(F4>0,F4/D4,0) | K4: =IF(G4>0,G4/D4,0)
A5: Mar-25 | B5: Overall | C5: 7611 | D5: 215386981 | E5: 155000000 | F5: 95000000 | G5: 0 | H5: 34215 | I5: =IF(E5>0,E5/D5,0) | J5: =IF(F5>0,F5/D5,0) | K5: =IF(G5>0,G5/D5,0)
A6: Apr-25 | B6: Overall | C6: 7080 | D6: 219206427 | E6: 150000000 | F6: 85000000 | G6: 0 | H6: 32438 | I6: =IF(E6>0,E6/D6,0) | J6: =IF(F6>0,F6/D6,0) | K6: =IF(G6>0,G6/D6,0)
A7: May-25 | B7: Overall | C7: 6417 | D7: 160878395 | E7: 110000000 | F7: 0 | G7: 0 | H7: 28962 | I7: =IF(E7>0,E7/D7,0) | J7: =IF(F7>0,F7/D7,0) | K7: =IF(G7>0,G7/D7,0)
A8: Jun-25 | B8: Overall | C8: 7310 | D8: 196390716 | E8: 130000000 | F8: 0 | G8: 0 | H8: 26871 | I8: =IF(E8>0,E8/D8,0) | J8: =IF(F8>0,F8/D8,0) | K8: =IF(G8>0,G8/D8,0)
A9: Jul-25 | B9: Overall | C9: 7788 | D9: 197932414 | E9: 120000000 | F9: 0 | G9: 0 | H9: 25416 | I9: =IF(E9>0,E9/D9,0) | J9: =IF(F9>0,F9/D9,0) | K9: =IF(G9>0,G9/D9,0)
A10: Aug-25 | B10: Overall | C10: 8049 | D10: 176317559 | E10: 0 | F10: 0 | G10: 0 | H10: 21908 | I10: =IF(E10>0,E10/D10,0) | J10: =IF(F10>0,F10/D10,0) | K10: =IF(G10>0,G10/D10,0)
A11: Sep-25 | B11: Overall | C11: 7877 | D11: 207383745 | E11: 0 | F11: 0 | G11: 0 | H11: 26328 | I11: =IF(E11>0,E11/D11,0) | J11: =IF(F11>0,F11/D11,0) | K11: =IF(G11>0,G11/D11,0)
A12: Oct-25 | B12: Overall | C12: 7350 | D12: 216933118 | E12: 0 | F12: 0 | G12: 0 | H12: 29515 | I12: =IF(E12>0,E12/D12,0) | J12: =IF(F12>0,F12/D12,0) | K12: =IF(G12>0,G12/D12,0)

Sheet Derived_Metrics
A1: Stage | B1: Sub_Stage | C1: Metric | D1: TTM_Value | E1: 3M_Avg | F1: Unit | G1: Formula_Reference | H1: Source_Sheet
A2: A. ACQUISITION | B2: A1. Investment | C2: Total Spend (Cr) | D2: =Core_Digital!D14/10000000 | E2: =Core_Digital!D15/10000000 | F2: ₹ Cr | G2: SUM(Perf_Spends) | H2: Core_Digital
A3: A. ACQUISITION | B3: A1. Investment | C3: - Google Paid (Cr) | D3: =Google_Web!C14/10000000 | E3: =Google_Web!C14/3/10000000 | F3: ₹ Cr | G3: SUM(Google.Spends) | H3: Google_Web
A4: A. ACQUISITION | B4: A1. Investment | C4: - Meta Paid (Cr) | D4: =Meta_Web!C14/10000000 | E4: =Meta_Web!C14/3/10000000 | F4: ₹ Cr | G4: SUM(Meta.Spends) | H4: Meta_Web
A5: A. ACQUISITION | B5: A2. Leads | C5: Total Leads | D5: =Core_Digital!L14 | E5: =Core_Digital!L15 | F5: Count | G5: SUM(Leads) | H5: Core_Digital
A6: A. ACQUISITION | B6: A2. Leads | C6: - Google Paid | D6: =Google_Web!F14 | E6: =Google_Web!F14/12 | F6: Count | G6: SUM(Google.Leads) | H6: Google_Web
A7: A. ACQUISITION | B7: A2. Leads | C7: - Meta Paid | D7: =Meta_Web!F14 | E7: =Meta_Web!F14/12 | F7: Count | G7: SUM(Meta.Leads) | H7: Meta_Web
A8: A. ACQUISITION | B8: A2. Leads | C8: - Website Organic | D8: =Website_Organic!C14 | E8: =Website_Organic!C14/12 | F8: Count | G8: SUM(WebOrg.Leads) | H8: Website_Organic
A9: A. ACQUISITION | B9: A2. Leads | C9: - App Organic | D9: =App_Organic!C14 | E9: =App_Organic!C14/12 | F9: Count | G9: SUM(App.Leads) | H9: App_Organic
A10: A. ACQUISITION | B10: A2. Leads | C10: - GMB (Direct) | D10: =GMB!E14 | E10: =GMB!E14/12 | F10: Count | G10: SUM(GMB.Leads) | H10: GMB
A11: A. ACQUISITION | B11: A2. Leads | C11: - Aggregator | D11: =Aggregator!C14 | E11: =Aggregator!C14/12 | F11: Count | G11: SUM(Agg.Leads) | H11: Aggregator
A12: A. ACQUISITION | B12: A2. Leads | C12: Website Traffic Leads | D12: =Google_Web!F14+Meta_Web!F14+Website_Organic!C14+App_Organic!C14 | E12: =(Google_Web!F14+Meta_Web!F14+Website_Organic!C14+App_Organic!C14)/12 | F12: Count | G12: Google+Meta+WebOrg+App | H12: Calculated
A13: A. ACQUISITION | B13: A2. Leads | C13: CPL (Paid Only) | D13: =(Google_Web!C14+Meta_Web!C14)/(Google_Web!F14+Meta_Web!F14) | E13: =(Google_Web!C14+Meta_Web!C14)/(Google_Web!F14+Meta_Web!F14) | F13: ₹ | G13: PaidSpend/PaidLeads | H13: Calculated
A14: A. ACQUISITION | B14: A3. Website CVR | C14: L→AS Rate (Overall) | D14: =Core_Digital!M14/Core_Digital!L14 | E14: =Core_Digital!M15/Core_Digital!L15 | F14: % | G14: AS/Leads | H14: Core_Digital
A15: A. ACQUISITION | B15: A3. Website CVR | C15: L→AS Rate (Paid) | D15: =(Google_Web!G14+Meta_Web!G14)/(Google_Web!F14+Meta_Web!F14) | E15: =(Google_Web!G14+Meta_Web!G14)/(Google_Web!F14+Meta_Web!F14) | F15: % | G15: Paid.AS/Paid.Leads | H15: Calculated
A16: A. ACQUISITION | B16: A3. Website CVR | C16: L→AS Rate (Organic) | D16: =Website_Organic!D14/Website_Organic!C14 | E16: =Website_Organic!D14/Website_Organic!C14 | F16: % | G16: WebOrg.AS/WebOrg.Leads | H16: Website_Organic
A17: A. ACQUISITION | B17: A4. Appointments | C17: Total AS | D17: =Core_Digital!M14 | E17: =Core_Digital!M15 | F17: Count | G17: SUM(AS) | H17: Core_Digital
A18: A. ACQUISITION | B18: A4. Appointments | C18: - Paid AS | D18: =Google_Web!G14+Meta_Web!G14 | E18: =(Google_Web!G14+Meta_Web!G14)/12 | F18: Count | G18: Google.AS+Meta.AS | H18: Calculated
A19: A. ACQUISITION | B19: A4. Appointments | C19: - Organic AS | D19: =Core_Digital!M14-(Google_Web!G14+Meta_Web!G14) | E19: =Core_Digital!M15-(Google_Web!G14+Meta_Web!G14)/12 | F19: Count | G19: Total.AS - Paid.AS | H19: Calculated
A20: A. ACQUISITION | B20: A5. Show Rate | C20: AS→Walk-in Rate | D20: =Core_Digital!N14/Core_Digital!M14 | E20: =Core_Digital!N15/Core_Digital!M15 | F20: % | G20: Walkin/AS | H20: Core_Digital
A21: A. ACQUISITION | B21: A6. Walk-ins | C21: Total Walk-ins | D21: =Core_Digital!N14 | E21: =Core_Digital!N15 | F21: Count | G21: SUM(Walkin) | H21: Core_Digital
A22: A. ACQUISITION | B22: A7. Conversion | C22: Walk-in→NCA Rate | D22: =Core_Digital!V14/Core_Digital!N14 | E22: =Core_Digital!V15/Core_Digital!N15 | F22: % | G22: NCA/Walkin | H22: Core_Digital
A23: A. ACQUISITION | B23: A8. New Customers | C23: NCA | D23: =Core_Digital!V14 | E23: =Core_Digital!V15 | F23: Count | G23: SUM(NCA) | H23: Core_Digital
A24: E. ENGAGEMENT | B24: E1. Transactions | C24: Total Transactions | D24: =Core_Digital!AA14 | E24: =Core_Digital!AA15 | F24: Count | G24: SUM(Transactions) | H24: Core_Digital
A25: E. ENGAGEMENT | B25: E1. Transactions | C25: Txn per NCA | D25: =Core_Digital!AA14/Core_Digital!V14 | E25: =Core_Digital!AA15/Core_Digital!V15 | F25: Ratio | G25: Transactions/NCA | H25: Calculated
A26: E. ENGAGEMENT | B26: E2. AOV | C26: Overall AOV | D26: =Core_Digital!U14 | E26: =Core_Digital!U15 | F26: ₹ | G26: AVERAGE(AOV) | H26: Core_Digital
A27: E. ENGAGEMENT | B27: E2. AOV | C27: New Customer AOV | D27: =Core_Digital!W14/Core_Digital!V14 | E27: =Core_Digital!W15/Core_Digital!V15 | F27: ₹ | G27: NewRev/NCA | H27: Calculated
A28: R. RETENTION | B28: R1. LTV | C28: M0 LTV (First Visit) | D28: =Core_Digital!W14/Core_Digital!V14 | E28: =Core_Digital!W15/Core_Digital!V15 | F28: ₹ | G28: NewRev/NCA | H28: Core_Digital
A29: R. RETENTION | B29: R1. LTV | C29: M3 Retention % | D29: =Config!B9 | E29: =Config!B9 | F29: % | G29: Config.M3_Retention | H29: Config
A30: R. RETENTION | B30: R1. LTV | C30: M6 Retention % | D30: =Config!B10 | E30: =Config!B10 | F30: % | G30: Config.M6_Retention | H30: Config
A31: R. RETENTION | B31: R1. LTV | C31: M9 Retention % | D31: =Config!B11 | E31: =Config!B11 | F31: % | G31: Config.M9_Retention | H31: Config
A32: REVENUE | B32: Total | C32: Total Revenue (Cr) | D32: =Core_Digital!O14/10000000 | E32: =Core_Digital!O15/10000000 | F32: ₹ Cr | G32: SUM(Total_Rev) | H32: Core_Digital
A33: REVENUE | B33: Total | C33: New Customer Revenue (Cr) | D33: =Core_Digital!W14/10000000 | E33: =Core_Digital!W15/10000000 | F33: ₹ Cr | G33: SUM(New_Rev) | H33: Core_Digital
A34: REVENUE | B34: Total | C34: Existing Customer Revenue (Cr) | D34: =Core_Digital!P14/10000000 | E34: =Core_Digital!P15/10000000 | F34: ₹ Cr | G34: SUM(Exist_Rev) | H34: Core_Digital
A35: REVENUE | B35: Total | C35: New Rev % | D35: =Core_Digital!W14/Core_Digital!O14 | E35: =Core_Digital!W15/Core_Digital!O15 | F35: % | G35: NewRev/TotalRev | H35: Calculated
A36: REVENUE | B36: Total | C36: Existing Rev % | D36: =Core_Digital!P14/Core_Digital!O14 | E36: =Core_Digital!P15/Core_Digital!O15 | F36: % | G36: ExistRev/TotalRev | H36: Calculated
A37: REVENUE | B37: Total | C37: Blended ROI | D37: =Core_Digital!O14/Core_Digital!D14 | E37: =Core_Digital!O15/Core_Digital!D15 | F37: x | G37: TotalRev/Spend | H37: Calculated

Sheet Reconciliation
A1: Check_Name | B1: Expected | C1: Actual | D1: Difference | E1: Status | F1: Formula
A2: Total Leads = Sum of Channels | B2: =Core_Digital!L14 | C2: =Google_Web!F14+Meta_Web!F14+GMB!E14+Website_Organic!C14+Aggregator!C14+App_Organic!C14 | D2: =B2-C2 | E2: =IF(ABS(D2)<100,"✓ OK","✗ CHECK") | F2: Core.Leads vs Sum(Channel.Leads)
A3: Total Revenue = Sum of Channels | B3: =Core_Digital!O14 | C3: =Google_Web!I14+Meta_Web!I14+GMB!H14+Website_Organic!F14+Aggregator!F14+App_Organic!F14 | D3: =B3-C3 | E3: =IF(ABS(D3/B3)<0.05,"✓ OK","✗ CHECK") | F3: Core.Rev vs Sum(Channel.Rev)
A4: Total NCA = Sum of Channels | B4: =Core_Digital!V14 | C4: =Google_Web!K14+Meta_Web!K14+GMB!J14+Website_Organic!H14+Aggregator!H14+App_Organic!H14 | D4: =B4-C4 | E4: =IF(ABS(D4)<100,"✓ OK","✗ CHECK") | F4: Core.NCA vs Sum(Channel.NCA)
A5: Paid Spend = Google + Meta | B5: =Core_Digital!D14 | C5: =Google_Web!C14+Meta_Web!C14 | D5: =B5-C5 | E5: =IF(ABS(D5/B5)<0.05,"✓ OK","✗ CHECK") | F5: Core.Spend vs Google+Meta
A6: ROI Calculation Check | B6: =Core_Digital!T14 | C6: =Core_Digital!O14/Core_Digital!D14 | D6: =B6-C6 | E6: =IF(ABS(D6)<1,"✓ OK","✗ CHECK") | F6: Stored ROI vs Calculated ROI
A7: NCA% Calculation Check | B7: =Core_Digital!Z14/100 | C7: =Core_Digital!V14/Core_Digital!N14 | D7: =B7-C7 | E7: =IF(ABS(D7)<0.01,"✓ OK","✗ CHECK") | F7: Stored NCA% vs NCA/Walkin
A8: New Rev = NCA × New AOV | B8: =Core_Digital!W14 | C8: =Core_Digital!V14*Core_Digital!Y14 | D8: =B8-C8 | E8: =IF(ABS(D8/B8)<0.1,"✓ OK","✗ CHECK") | F8: New_Rev vs NCA×New_AOV

Sheet Channel_Summary
A1: Channel | B1: TTM_Leads | C1: TTM_AS | D1: TTM_Walkin | E1: TTM_Revenue | F1: TTM_NCA | G1: TTM_New_Rev | H1: Lead_Share% | I1: Rev_Share% | J1: L_to_AS% | K1: AS_to_WI% | L1: NCA%
A2: Google Paid | B2: =Google_Web!F14 | C2: =Google_Web!G14 | D2: =Google_Web!H14 | E2: =Google_Web!I14 | F2: =Google_Web!K14 | G2: =Google_Web!L14 | H2: =B2/SUM($B$2:$B$7) | I2: =E2/SUM($E$2:$E$7) | J2: =C2/B2 | K2: =D2/C2 | L2: =F2/D2
A3: Meta Paid | B3: =Meta_Web!F14 | C3: =Meta_Web!G14 | D3: =Meta_Web!H14 | E3: =Meta_Web!I14 | F3: =Meta_Web!K14 | G3: =Meta_Web!L14 | H3: =B3/SUM($B$2:$B$7) | I3: =E3/SUM($E$2:$E$7) | J3: =C3/B3 | K3: =D3/C3 | L3: =F3/D3
A4: GMB | B4: =GMB!E14 | C4: =GMB!F14 | D4: =GMB!G14 | E4: =GMB!H14 | F4: =GMB!J14 | G4: =GMB!K14 | H4: =B4/SUM($B$2:$B$7) | I4: =E4/SUM($E$2:$E$7) | J4: =C4/B4 | K4: =D4/C4 | L4: =F4/D4
A5: Website Organic | B5: =Website_Organic!C14 | C5: =Website_Organic!D14 | D5: =Website_Organic!E14 | E5: =Website_Organic!F14 | F5: =Website_Organic!H14 | G5: =Website_Organic!I14 | H5: =B5/SUM($B$2:$B$7) | I5: =E5/SUM($E$2:$E$7) | J5: =C5/B5 | K5: =D5/C5 | L5: =F5/D5
A6: Aggregator | B6: =Aggregator!C14 | C6: =Aggregator!D14 | D6: =Aggregator!E14 | E6: =Aggregator!F14 | F6: =Aggregator!H14 | G6: =Aggregator!I14 | H6: =B6/SUM($B$2:$B$7) | I6: =E6/SUM($E$2:$E$7) | J6: =C6/B6 | K6: =D6/C6 | L6: =F6/D6
A7: App Organic | B7: =App_Organic!C14 | C7: =App_Organic!D14 | D7: =App_Organic!E14 | E7: =App_Organic!F14 | F7: =App_Organic!H14 | G7: =App_Organic!I14 | H7: =B7/SUM($B$2:$B$7) | I7: =E7/SUM($E$2:$E$7) | J7: =C7/B7 | K7: =D7/C7 | L7: =F7/D7
A8: TOTAL | B8: =SUM(B2:B7) | C8: =SUM(C2:C7) | D8: =SUM(D2:D7) | E8: =SUM(E2:E7) | F8: =SUM(F2:F7) | G8: =SUM(G2:G7) | H8: =SUM(H2:H7) | I8: =SUM(I2:I7) | J8: =C8/B8 | K8: =D8/C8 | L8: =F8/D8
